mymath_utils/__init__.py
mymath_utils/calculator.py
piyush_math_calculator-0.1.0.dist-info/licenses/LICENSE
piyush_math_calculator-0.1.0.dist-info/METADATA
piyush_math_calculator-0.1.0.dist-info/WHEEL
piyush_math_calculator-0.1.0.dist-info/entry_points.txt
piyush_math_calculator-0.1.0.dist-info/top_level.txt
piyush_math_calculator-0.1.0.dist-info/RECORD
